{
  "project_info": {
    "project_number": "1034864461202",
    "firebase_url": "https://rentapp-c12ed.firebaseio.com",
    "project_id": "rentapp-c12ed",
    "storage_bucket": "rentapp-c12ed.appspot.com"
  },
  "client": [
    {
      "client_info": {
        "mobilesdk_app_id": "1:1034864461202:android:b7e2902ec699d9bc69ad4b",
        "android_client_info": {
          "package_name": "com.example.rent_app"
        }
      },
      "oauth_client": [
        {
          "client_id": "1034864461202-mcl5l0il24hg82p486og25qj5ji9s994.apps.googleusercontent.com",
          "client_type": 3
        }
      ],
      "api_key": [
        {
          "current_key": "AIzaSyDzEseeVrHYXdthR9sxgCbvvYTkyrr3w74"
        }
      ],
      "services": {
        "appinvite_service": {
          "other_platform_oauth_client": [
            {
              "client_id": "1034864461202-mcl5l0il24hg82p486og25qj5ji9s994.apps.googleusercontent.com",
              "client_type": 3
            }
          ]
        }
      }
    }
  ],
  "configuration_version": "1"
}